matrix_photos/__init__.py
matrix_photos/__main__.py
matrix_photos/admin_command_handler.py
matrix_photos/configuration.py
matrix_photos/file_convert.py
matrix_photos/photos_client.py
matrix_photos/storage_strategy.py
matrix_photos/text_message_command_handler.py
matrix_photos/utils.py
matrix_photos-0.0.4.dist-info/LICENSE
matrix_photos-0.0.4.dist-info/METADATA
matrix_photos-0.0.4.dist-info/WHEEL
matrix_photos-0.0.4.dist-info/entry_points.txt
matrix_photos-0.0.4.dist-info/top_level.txt
matrix_photos-0.0.4.dist-info/RECORD
