Metadata-Version: 2.1
Name: matrix-photos
Version: 0.0.4
Summary: A matrix client for the photOS DIY photoframe
Home-page: https://github.com/universalappfactory/matrix-photos
Author: universalappfactory
Author-email: info@universalappfactory.de
License: GPL, Version 3.0
Platform: UNKNOWN
Classifier: Environment :: No Input/Output (Daemon)
Classifier: Intended Audience :: End Users/Desktop
Classifier: Operating System :: OS Independent
Classifier: Programming Language :: Python :: 3
Classifier: Programming Language :: Python :: 3.7
Classifier: Programming Language :: Python :: 3.8
Classifier: Programming Language :: Python :: 3.9
Classifier: Topic :: Multimedia :: Graphics
Classifier: Topic :: Communications :: Chat
Classifier: Topic :: Communications :: File Sharing
Classifier: Topic :: Multimedia :: Graphics
Requires-Python: >=3.7
License-File: LICENSE
Requires-Dist: mautrix (==0.14.7)
Requires-Dist: aiohttp (<4,>=3)
Requires-Dist: aiosqlite (<0.18,>=0.16)
Requires-Dist: python-olm (<4,>=3)
Requires-Dist: pycryptodome (<4,>=3)
Requires-Dist: unpaddedbase64 (<2,>=1)
Requires-Dist: psycopg2-binary (<3,>=2)
Requires-Dist: asyncpg (<0.26,>=0.20)
Requires-Dist: SQLAlchemy (<1.4,>=1)
Requires-Dist: pyyaml (==6.0)
Provides-Extra: lint
Requires-Dist: pylint ; extra == 'lint'
Requires-Dist: pep8 ; extra == 'lint'
